hark_lang/__init__.py
hark_lang/cli/__init__.py
hark_lang/cli/hosted_query.py
hark_lang/cli/in_hosted.py
hark_lang/cli/in_own.py
hark_lang/cli/interface.py
hark_lang/cli/main.py
hark_lang/cli/utils.py
hark_lang/cloud/__init__.py
hark_lang/cloud/api.py
hark_lang/cloud/aws.py
hark_lang/config.py
hark_lang/config_classes.py
hark_lang/controllers/__init__.py
hark_lang/controllers/ddb.py
hark_lang/controllers/ddb_model.py
hark_lang/controllers/local.py
hark_lang/dist_data/hark.toml
hark_lang/dist_data/hark_lambda.zip
hark_lang/exceptions.py
hark_lang/executors/__init__.py
hark_lang/executors/awslambda.py
hark_lang/executors/multiprocess.py
hark_lang/executors/thread.py
hark_lang/hark_compiler/__init__.py
hark_lang/hark_compiler/attributes.py
hark_lang/hark_compiler/compiler.py
hark_lang/hark_parser/__init__.py
hark_lang/hark_parser/nodes.py
hark_lang/hark_parser/parser.py
hark_lang/hark_parser/repls.py
hark_lang/load.py
hark_lang/machine/__init__.py
hark_lang/machine/arec.py
hark_lang/machine/controller.py
hark_lang/machine/executable.py
hark_lang/machine/foreign.py
hark_lang/machine/future.py
hark_lang/machine/hark_serialisable.py
hark_lang/machine/instruction.py
hark_lang/machine/instructionset.py
hark_lang/machine/machine.py
hark_lang/machine/probe.py
hark_lang/machine/state.py
hark_lang/machine/stdout_item.py
hark_lang/machine/thread_failure.py
hark_lang/machine/types.py
hark_lang/run/__init__.py
hark_lang/run/aws.py
hark_lang/run/common.py
hark_lang/run/dynamodb.py
hark_lang/run/lambda_handlers.py
hark_lang/run/local.py
src/hark_lang/dist_data/hark_lambda.zip
hark_lang-0.5.1.dist-info/entry_points.txt
hark_lang-0.5.1.dist-info/LICENSE
hark_lang-0.5.1.dist-info/WHEEL
hark_lang-0.5.1.dist-info/METADATA
hark_lang-0.5.1.dist-info/RECORD
