Metadata-Version: 2.1
Name: hark-lang
Version: 0.5.1
Summary: The Hark Programming Language
Home-page: https://www.condense9.com
License: Apache-2.0
Keywords: serverless,orchestration,concurrency,aws,language
Author: Ric da Silva
Author-email: ric@condense9.com
Maintainer: Ric da Silva
Maintainer-email: ric@condense9.com
Requires-Python: >=3.8,<4.0
Classifier: Development Status :: 3 - Alpha
Classifier: Intended Audience :: Developers
Classifier: License :: OSI Approved :: Apache Software License
Classifier: Programming Language :: Python :: 3
Classifier: Programming Language :: Python :: 3.8
Classifier: Topic :: Software Development
Requires-Dist: PyInquirer (>=1.0.3,<2.0.0)
Requires-Dist: boto3
Requires-Dist: botocore
Requires-Dist: coloredlogs (>=14.0,<15.0)
Requires-Dist: colorful (>=0.5.4,<0.6.0)
Requires-Dist: deterministic_zip (>=0.1,<0.2)
Requires-Dist: docopt
Requires-Dist: gql (>=2.0.0,<3.0.0)
Requires-Dist: graphviz (>=0.13.2,<0.14.0)
Requires-Dist: parsy (>=1.3.0,<2.0.0)
Requires-Dist: pydot (>=1.4.1,<2.0.0)
Requires-Dist: pynamodb
Requires-Dist: pyyaml (>=5.3.1,<6.0.0)
Requires-Dist: schema (>=0.7.2,<0.8.0)
Requires-Dist: sly (>=0.4,<0.5)
Requires-Dist: texttable (>=1.6.2,<2.0.0)
Requires-Dist: toml (>=0.10.1,<0.11.0)
Requires-Dist: yaspin (>=0.17.0,<0.18.0)
Project-URL: Bug Tracker, https://github.com/condense9/hark-lang/issues
Project-URL: Changelog, https://github.com/condense9/hark-lang/blob/master/CHANGELOG.md
Project-URL: Repository, https://github.com/condense9/hark-lang
